{
  "item": [
    {
      "id": "8ea730ec-d795-4f87-997b-5d6c46af8c53",
      "name": "Assignments",
      "description": {
        "content": "",
        "type": "text/plain"
      },
      "item": [
        {
          "id": "6e10b9f5-7694-420b-a65b-cbb162f60715",
          "name": "Workday Integration Retrieve learning assignments for a worker",
          "request": {
            "name": "Workday Integration Retrieve learning assignments for a worker",
            "description": {
              "content": "Returns the learning assignments for the specified worker.",
              "type": "text/plain"
            },
            "url": {
              "path": [
                "workers",
                ":ID",
                "learningAssignments"
              ],
              "host": [
                "{{baseUrl}}"
              ],
              "query": [
                {
                  "disabled": false,
                  "key": "limit",
                  "value": "20"
                },
                {
                  "disabled": false,
                  "key": "offset",
                  "value": "0"
                }
              ],
              "variable": [
                {
                  "disabled": false,
                  "type": "any",
                  "value": "<string>",
                  "key": "ID",
                  "description": "(Required) "
                },
                {
                  "description": {
                    "content": "",
                    "type": "text/plain"
                  },
                  "type": "any",
                  "value": "{{baseUrl}}",
                  "key": "baseUrl"
                },
                {
                  "description": {
                    "content": "",
                    "type": "text/plain"
                  },
                  "type": "any",
                  "value": "{{tenant}}",
                  "key": "tenant"
                }
              ]
            },
            "header": [
              {
                "key": "Accept",
                "value": "application/json"
              }
            ],
            "method": "GET",
            "auth": null
          },
          "response": [
            {
              "id": "940c3faa-b1ee-4dcb-9a1c-ce2f92e36519",
              "name": "Successful response with learning assignments",
              "originalRequest": {
                "url": {
                  "path": [
                    "workers",
                    ":ID",
                    "learningAssignments"
                  ],
                  "host": [
                    "{{baseUrl}}"
                  ],
                  "query": [
                    {
                      "key": "limit",
                      "value": "20"
                    },
                    {
                      "key": "offset",
                      "value": "0"
                    }
                  ],
                  "variable": [
                    {
                      "disabled": false,
                      "type": "any",
                      "value": "<string>",
                      "key": "ID",
                      "description": "(Required) "
                    },
                    {
                      "description": {
                        "content": "",
                        "type": "text/plain"
                      },
                      "type": "any",
                      "value": "{{baseUrl}}",
                      "key": "baseUrl"
                    },
                    {
                      "description": {
                        "content": "",
                        "type": "text/plain"
                      },
                      "type": "any",
                      "value": "{{tenant}}",
                      "key": "tenant"
                    }
                  ]
                },
                "header": [
                  {
                    "description": {
                      "content": "Added as a part of security scheme: oauth2",
                      "type": "text/plain"
                    },
                    "key": "Authorization",
                    "value": "<token>"
                  },
                  {
                    "key": "Accept",
                    "value": "application/json"
                  }
                ],
                "method": "GET",
                "body": {}
              },
              "status": "OK",
              "code": 200,
              "header": [
                {
                  "key": "Content-Type",
                  "value": "application/json"
                }
              ],
              "body": "{\n  \"total\": 9533,\n  \"data\": [\n    {\n      \"id\": \"string\",\n      \"course\": {\n        \"id\": \"string\",\n        \"descriptor\": \"string\",\n        \"href\": \"https://lYCXacDgknsAzfxoLH.ozOZG3-D286cmGIxfJzU5LImd9bvqBo-AMgkVdu\"\n      },\n      \"assignedDate\": \"1977-05-25\",\n      \"dueDate\": \"1951-09-22\",\n      \"status\": \"string\"\n    },\n    {\n      \"id\": \"string\",\n      \"course\": {\n        \"id\": \"string\",\n        \"descriptor\": \"string\",\n        \"href\": \"http://C.hjeAL8gqY2BaHotqv\"\n      },\n      \"assignedDate\": \"1999-02-12\",\n      \"dueDate\": \"1969-01-29\",\n      \"status\": \"string\"\n    }\n  ]\n}",
              "cookie": [],
              "_postman_previewlanguage": "json"
            },
            {
              "id": "da9f5701-9f16-4283-9279-71841be46bb8",
              "name": "Authentication required",
              "originalRequest": {
                "url": {
                  "path": [
                    "workers",
                    ":ID",
                    "learningAssignments"
                  ],
                  "host": [
                    "{{baseUrl}}"
                  ],
                  "query": [
                    {
                      "key": "limit",
                      "value": "20"
                    },
                    {
                      "key": "offset",
                      "value": "0"
                    }
                  ],
                  "variable": [
                    {
                      "disabled": false,
                      "type": "any",
                      "value": "<string>",
                      "key": "ID",
                      "description": "(Required) "
                    },
                    {
                      "description": {
                        "content": "",
                        "type": "text/plain"
                      },
                      "type": "any",
                      "value": "{{baseUrl}}",
                      "key": "baseUrl"
                    },
                    {
                      "description": {
                        "content": "",
                        "type": "text/plain"
                      },
                      "type": "any",
                      "value": "{{tenant}}",
                      "key": "tenant"
                    }
                  ]
                },
                "header": [
                  {
                    "description": {
                      "content": "Added as a part of security scheme: oauth2",
                      "type": "text/plain"
                    },
                    "key": "Authorization",
                    "value": "<token>"
                  },
                  {
                    "key": "Accept",
                    "value": "application/json"
                  }
                ],
                "method": "GET",
                "body": {}
              },
              "status": "Unauthorized",
              "code": 401,
              "header": [
                {
                  "key": "Content-Type",
                  "value": "application/json"
                }
              ],
              "body": "{\n  \"error\": \"string\"\n}",
              "cookie": [],
              "_postman_previewlanguage": "json"
            },
            {
              "id": "3ac0aa20-d09a-4ebf-bb53-23e3687e36f2",
              "name": "Insufficient permissions",
              "originalRequest": {
                "url": {
                  "path": [
                    "workers",
                    ":ID",
                    "learningAssignments"
                  ],
                  "host": [
                    "{{baseUrl}}"
                  ],
                  "query": [
                    {
                      "key": "limit",
                      "value": "20"
                    },
                    {
                      "key": "offset",
                      "value": "0"
                    }
                  ],
                  "variable": [
                    {
                      "disabled": false,
                      "type": "any",
                      "value": "<string>",
                      "key": "ID",
                      "description": "(Required) "
                    },
                    {
                      "description": {
                        "content": "",
                        "type": "text/plain"
                      },
                      "type": "any",
                      "value": "{{baseUrl}}",
                      "key": "baseUrl"
                    },
                    {
                      "description": {
                        "content": "",
                        "type": "text/plain"
                      },
                      "type": "any",
                      "value": "{{tenant}}",
                      "key": "tenant"
                    }
                  ]
                },
                "header": [
                  {
                    "description": {
                      "content": "Added as a part of security scheme: oauth2",
                      "type": "text/plain"
                    },
                    "key": "Authorization",
                    "value": "<token>"
                  },
                  {
                    "key": "Accept",
                    "value": "application/json"
                  }
                ],
                "method": "GET",
                "body": {}
              },
              "status": "Forbidden",
              "code": 403,
              "header": [
                {
                  "key": "Content-Type",
                  "value": "application/json"
                }
              ],
              "body": "{\n  \"error\": \"string\"\n}",
              "cookie": [],
              "_postman_previewlanguage": "json"
            },
            {
              "id": "d0e4e3ab-166d-44c3-81f5-bded065d32c7",
              "name": "Resource not found",
              "originalRequest": {
                "url": {
                  "path": [
                    "workers",
                    ":ID",
                    "learningAssignments"
                  ],
                  "host": [
                    "{{baseUrl}}"
                  ],
                  "query": [
                    {
                      "key": "limit",
                      "value": "20"
                    },
                    {
                      "key": "offset",
                      "value": "0"
                    }
                  ],
                  "variable": [
                    {
                      "disabled": false,
                      "type": "any",
                      "value": "<string>",
                      "key": "ID",
                      "description": "(Required) "
                    },
                    {
                      "description": {
                        "content": "",
                        "type": "text/plain"
                      },
                      "type": "any",
                      "value": "{{baseUrl}}",
                      "key": "baseUrl"
                    },
                    {
                      "description": {
                        "content": "",
                        "type": "text/plain"
                      },
                      "type": "any",
                      "value": "{{tenant}}",
                      "key": "tenant"
                    }
                  ]
                },
                "header": [
                  {
                    "description": {
                      "content": "Added as a part of security scheme: oauth2",
                      "type": "text/plain"
                    },
                    "key": "Authorization",
                    "value": "<token>"
                  },
                  {
                    "key": "Accept",
                    "value": "application/json"
                  }
                ],
                "method": "GET",
                "body": {}
              },
              "status": "Not Found",
              "code": 404,
              "header": [
                {
                  "key": "Content-Type",
                  "value": "application/json"
                }
              ],
              "body": "{\n  \"error\": \"string\"\n}",
              "cookie": [],
              "_postman_previewlanguage": "json"
            }
          ],
          "event": [],
          "protocolProfileBehavior": {
            "disableBodyPruning": true
          }
        }
      ],
      "event": []
    },
    {
      "id": "d1826d99-ab7f-4ab8-84f7-8f6f0bac4cfd",
      "name": "Completions",
      "description": {
        "content": "",
        "type": "text/plain"
      },
      "item": [
        {
          "id": "e401ea49-0cf8-4dd6-902b-27bfdd56016e",
          "name": "Workday Integration Retrieve learning completions for a worker",
          "request": {
            "name": "Workday Integration Retrieve learning completions for a worker",
            "description": {
              "content": "Returns the learning completion records for the specified worker.",
              "type": "text/plain"
            },
            "url": {
              "path": [
                "workers",
                ":ID",
                "learningCompletions"
              ],
              "host": [
                "{{baseUrl}}"
              ],
              "query": [
                {
                  "disabled": false,
                  "key": "limit",
                  "value": "20"
                },
                {
                  "disabled": false,
                  "key": "offset",
                  "value": "0"
                }
              ],
              "variable": [
                {
                  "disabled": false,
                  "type": "any",
                  "value": "<string>",
                  "key": "ID",
                  "description": "(Required) "
                },
                {
                  "description": {
                    "content": "",
                    "type": "text/plain"
                  },
                  "type": "any",
                  "value": "{{baseUrl}}",
                  "key": "baseUrl"
                },
                {
                  "description": {
                    "content": "",
                    "type": "text/plain"
                  },
                  "type": "any",
                  "value": "{{tenant}}",
                  "key": "tenant"
                }
              ]
            },
            "header": [
              {
                "key": "Accept",
                "value": "application/json"
              }
            ],
            "method": "GET",
            "auth": null
          },
          "response": [
            {
              "id": "8fc6b51f-2687-42b5-ba2c-8b0fbbc7ae7f",
              "name": "Successful response with learning completions",
              "originalRequest": {
                "url": {
                  "path": [
                    "workers",
                    ":ID",
                    "learningCompletions"
                  ],
                  "host": [
                    "{{baseUrl}}"
                  ],
                  "query": [
                    {
                      "key": "limit",
                      "value": "20"
                    },
                    {
                      "key": "offset",
                      "value": "0"
                    }
                  ],
                  "variable": [
                    {
                      "disabled": false,
                      "type": "any",
                      "value": "<string>",
                      "key": "ID",
                      "description": "(Required) "
                    },
                    {
                      "description": {
                        "content": "",
                        "type": "text/plain"
                      },
                      "type": "any",
                      "value": "{{baseUrl}}",
                      "key": "baseUrl"
                    },
                    {
                      "description": {
                        "content": "",
                        "type": "text/plain"
                      },
                      "type": "any",
                      "value": "{{tenant}}",
                      "key": "tenant"
                    }
                  ]
                },
                "header": [
                  {
                    "description": {
                      "content": "Added as a part of security scheme: oauth2",
                      "type": "text/plain"
                    },
                    "key": "Authorization",
                    "value": "<token>"
                  },
                  {
                    "key": "Accept",
                    "value": "application/json"
                  }
                ],
                "method": "GET",
                "body": {}
              },
              "status": "OK",
              "code": 200,
              "header": [
                {
                  "key": "Content-Type",
                  "value": "application/json"
                }
              ],
              "body": "{\n  \"total\": 2232,\n  \"data\": [\n    {\n      \"id\": \"string\",\n      \"course\": {\n        \"id\": \"string\",\n        \"descriptor\": \"string\",\n        \"href\": \"https://Qv.yahsazCpRKPjSX4jt+z1hDmksn0KeFC7z+Jbb8QlE,g\"\n      },\n      \"completionDate\": \"2008-11-29\",\n      \"grade\": \"string\"\n    },\n    {\n      \"id\": \"string\",\n      \"course\": {\n        \"id\": \"string\",\n        \"descriptor\": \"string\",\n        \"href\": \"https://mVzIHSVpETuyCFqyQs.uwrHCUC1qJqJMFFseW7toTcICSlFRFC\"\n      },\n      \"completionDate\": \"1983-08-28\",\n      \"grade\": \"string\"\n    }\n  ]\n}",
              "cookie": [],
              "_postman_previewlanguage": "json"
            },
            {
              "id": "fc181aa8-76eb-4f06-a0e7-c295566d4b1a",
              "name": "Authentication required",
              "originalRequest": {
                "url": {
                  "path": [
                    "workers",
                    ":ID",
                    "learningCompletions"
                  ],
                  "host": [
                    "{{baseUrl}}"
                  ],
                  "query": [
                    {
                      "key": "limit",
                      "value": "20"
                    },
                    {
                      "key": "offset",
                      "value": "0"
                    }
                  ],
                  "variable": [
                    {
                      "disabled": false,
                      "type": "any",
                      "value": "<string>",
                      "key": "ID",
                      "description": "(Required) "
                    },
                    {
                      "description": {
                        "content": "",
                        "type": "text/plain"
                      },
                      "type": "any",
                      "value": "{{baseUrl}}",
                      "key": "baseUrl"
                    },
                    {
                      "description": {
                        "content": "",
                        "type": "text/plain"
                      },
                      "type": "any",
                      "value": "{{tenant}}",
                      "key": "tenant"
                    }
                  ]
                },
                "header": [
                  {
                    "description": {
                      "content": "Added as a part of security scheme: oauth2",
                      "type": "text/plain"
                    },
                    "key": "Authorization",
                    "value": "<token>"
                  },
                  {
                    "key": "Accept",
                    "value": "application/json"
                  }
                ],
                "method": "GET",
                "body": {}
              },
              "status": "Unauthorized",
              "code": 401,
              "header": [
                {
                  "key": "Content-Type",
                  "value": "application/json"
                }
              ],
              "body": "{\n  \"error\": \"string\"\n}",
              "cookie": [],
              "_postman_previewlanguage": "json"
            },
            {
              "id": "b529b4d3-ed77-4c15-937d-7f77f40c7919",
              "name": "Insufficient permissions",
              "originalRequest": {
                "url": {
                  "path": [
                    "workers",
                    ":ID",
                    "learningCompletions"
                  ],
                  "host": [
                    "{{baseUrl}}"
                  ],
                  "query": [
                    {
                      "key": "limit",
                      "value": "20"
                    },
                    {
                      "key": "offset",
                      "value": "0"
                    }
                  ],
                  "variable": [
                    {
                      "disabled": false,
                      "type": "any",
                      "value": "<string>",
                      "key": "ID",
                      "description": "(Required) "
                    },
                    {
                      "description": {
                        "content": "",
                        "type": "text/plain"
                      },
                      "type": "any",
                      "value": "{{baseUrl}}",
                      "key": "baseUrl"
                    },
                    {
                      "description": {
                        "content": "",
                        "type": "text/plain"
                      },
                      "type": "any",
                      "value": "{{tenant}}",
                      "key": "tenant"
                    }
                  ]
                },
                "header": [
                  {
                    "description": {
                      "content": "Added as a part of security scheme: oauth2",
                      "type": "text/plain"
                    },
                    "key": "Authorization",
                    "value": "<token>"
                  },
                  {
                    "key": "Accept",
                    "value": "application/json"
                  }
                ],
                "method": "GET",
                "body": {}
              },
              "status": "Forbidden",
              "code": 403,
              "header": [
                {
                  "key": "Content-Type",
                  "value": "application/json"
                }
              ],
              "body": "{\n  \"error\": \"string\"\n}",
              "cookie": [],
              "_postman_previewlanguage": "json"
            },
            {
              "id": "07b3f30a-a394-4ba0-8f80-cbbdd88bc140",
              "name": "Resource not found",
              "originalRequest": {
                "url": {
                  "path": [
                    "workers",
                    ":ID",
                    "learningCompletions"
                  ],
                  "host": [
                    "{{baseUrl}}"
                  ],
                  "query": [
                    {
                      "key": "limit",
                      "value": "20"
                    },
                    {
                      "key": "offset",
                      "value": "0"
                    }
                  ],
                  "variable": [
                    {
                      "disabled": false,
                      "type": "any",
                      "value": "<string>",
                      "key": "ID",
                      "description": "(Required) "
                    },
                    {
                      "description": {
                        "content": "",
                        "type": "text/plain"
                      },
                      "type": "any",
                      "value": "{{baseUrl}}",
                      "key": "baseUrl"
                    },
                    {
                      "description": {
                        "content": "",
                        "type": "text/plain"
                      },
                      "type": "any",
                      "value": "{{tenant}}",
                      "key": "tenant"
                    }
                  ]
                },
                "header": [
                  {
                    "description": {
                      "content": "Added as a part of security scheme: oauth2",
                      "type": "text/plain"
                    },
                    "key": "Authorization",
                    "value": "<token>"
                  },
                  {
                    "key": "Accept",
                    "value": "application/json"
                  }
                ],
                "method": "GET",
                "body": {}
              },
              "status": "Not Found",
              "code": 404,
              "header": [
                {
                  "key": "Content-Type",
                  "value": "application/json"
                }
              ],
              "body": "{\n  \"error\": \"string\"\n}",
              "cookie": [],
              "_postman_previewlanguage": "json"
            }
          ],
          "event": [],
          "protocolProfileBehavior": {
            "disableBodyPruning": true
          }
        }
      ],
      "event": []
    },
    {
      "id": "931672d6-99e7-4cb7-b825-a221ac1d5ca2",
      "name": "Courses",
      "description": {
        "content": "",
        "type": "text/plain"
      },
      "item": [
        {
          "id": "82188518-7e58-493b-9294-0725dc512901",
          "name": "Workday Integration Retrieve learning courses",
          "request": {
            "name": "Workday Integration Retrieve learning courses",
            "description": {
              "content": "Returns a collection of learning courses available in the catalog.",
              "type": "text/plain"
            },
            "url": {
              "path": [
                "learningCourses"
              ],
              "host": [
                "{{baseUrl}}"
              ],
              "query": [
                {
                  "disabled": false,
                  "key": "limit",
                  "value": "20"
                },
                {
                  "disabled": false,
                  "key": "offset",
                  "value": "0"
                },
                {
                  "disabled": false,
                  "key": "search",
                  "value": "<string>"
                }
              ],
              "variable": [
                {
                  "description": {
                    "content": "",
                    "type": "text/plain"
                  },
                  "type": "any",
                  "value": "{{baseUrl}}",
                  "key": "baseUrl"
                },
                {
                  "description": {
                    "content": "",
                    "type": "text/plain"
                  },
                  "type": "any",
                  "value": "{{tenant}}",
                  "key": "tenant"
                }
              ]
            },
            "header": [
              {
                "key": "Accept",
                "value": "application/json"
              }
            ],
            "method": "GET",
            "auth": null
          },
          "response": [
            {
              "id": "bbd5fef2-f369-4bbf-a7ef-4432c7071565",
              "name": "Successful response with learning courses",
              "originalRequest": {
                "url": {
                  "path": [
                    "learningCourses"
                  ],
                  "host": [
                    "{{baseUrl}}"
                  ],
                  "query": [
                    {
                      "key": "limit",
                      "value": "20"
                    },
                    {
                      "key": "offset",
                      "value": "0"
                    },
                    {
                      "key": "search",
                      "value": "<string>"
                    }
                  ],
                  "variable": [
                    {
                      "description": {
                        "content": "",
                        "type": "text/plain"
                      },
                      "type": "any",
                      "value": "{{baseUrl}}",
                      "key": "baseUrl"
                    },
                    {
                      "description": {
                        "content": "",
                        "type": "text/plain"
                      },
                      "type": "any",
                      "value": "{{tenant}}",
                      "key": "tenant"
                    }
                  ]
                },
                "header": [
                  {
                    "description": {
                      "content": "Added as a part of security scheme: oauth2",
                      "type": "text/plain"
                    },
                    "key": "Authorization",
                    "value": "<token>"
                  },
                  {
                    "key": "Accept",
                    "value": "application/json"
                  }
                ],
                "method": "GET",
                "body": {}
              },
              "status": "OK",
              "code": 200,
              "header": [
                {
                  "key": "Content-Type",
                  "value": "application/json"
                }
              ],
              "body": "{\n  \"total\": 7318,\n  \"data\": [\n    {\n      \"id\": \"string\",\n      \"descriptor\": \"string\",\n      \"title\": \"string\",\n      \"description\": \"string\",\n      \"courseType\": {\n        \"id\": \"string\",\n        \"descriptor\": \"string\",\n        \"href\": \"https://kaFSUInYnVipUmfQpPQrZlYXrUfUlU.gptDJNy7nJnxNb+2+AKIYMOwf4mey1DaxI53kWBROPMLcIuByR-s0.HBqsQzC6PiNzm\"\n      },\n      \"duration\": \"string\",\n      \"isActive\": true\n    },\n    {\n      \"id\": \"string\",\n      \"descriptor\": \"string\",\n      \"title\": \"string\",\n      \"description\": \"string\",\n      \"courseType\": {\n        \"id\": \"string\",\n        \"descriptor\": \"string\",\n        \"href\": \"https://QjYBGvycY.ythtQaUcqYYBI.82.U+XXp48ULiD\"\n      },\n      \"duration\": \"string\",\n      \"isActive\": false\n    }\n  ]\n}",
              "cookie": [],
              "_postman_previewlanguage": "json"
            },
            {
              "id": "7fd295f1-f239-40f4-8182-92f70fbdc027",
              "name": "Authentication required",
              "originalRequest": {
                "url": {
                  "path": [
                    "learningCourses"
                  ],
                  "host": [
                    "{{baseUrl}}"
                  ],
                  "query": [
                    {
                      "key": "limit",
                      "value": "20"
                    },
                    {
                      "key": "offset",
                      "value": "0"
                    },
                    {
                      "key": "search",
                      "value": "<string>"
                    }
                  ],
                  "variable": [
                    {
                      "description": {
                        "content": "",
                        "type": "text/plain"
                      },
                      "type": "any",
                      "value": "{{baseUrl}}",
                      "key": "baseUrl"
                    },
                    {
                      "description": {
                        "content": "",
                        "type": "text/plain"
                      },
                      "type": "any",
                      "value": "{{tenant}}",
                      "key": "tenant"
                    }
                  ]
                },
                "header": [
                  {
                    "description": {
                      "content": "Added as a part of security scheme: oauth2",
                      "type": "text/plain"
                    },
                    "key": "Authorization",
                    "value": "<token>"
                  },
                  {
                    "key": "Accept",
                    "value": "application/json"
                  }
                ],
                "method": "GET",
                "body": {}
              },
              "status": "Unauthorized",
              "code": 401,
              "header": [
                {
                  "key": "Content-Type",
                  "value": "application/json"
                }
              ],
              "body": "{\n  \"error\": \"string\"\n}",
              "cookie": [],
              "_postman_previewlanguage": "json"
            },
            {
              "id": "988dc598-fc9d-4e2b-8fdf-549022f42808",
              "name": "Insufficient permissions",
              "originalRequest": {
                "url": {
                  "path": [
                    "learningCourses"
                  ],
                  "host": [
                    "{{baseUrl}}"
                  ],
                  "query": [
                    {
                      "key": "limit",
                      "value": "20"
                    },
                    {
                      "key": "offset",
                      "value": "0"
                    },
                    {
                      "key": "search",
                      "value": "<string>"
                    }
                  ],
                  "variable": [
                    {
                      "description": {
                        "content": "",
                        "type": "text/plain"
                      },
                      "type": "any",
                      "value": "{{baseUrl}}",
                      "key": "baseUrl"
                    },
                    {
                      "description": {
                        "content": "",
                        "type": "text/plain"
                      },
                      "type": "any",
                      "value": "{{tenant}}",
                      "key": "tenant"
                    }
                  ]
                },
                "header": [
                  {
                    "description": {
                      "content": "Added as a part of security scheme: oauth2",
                      "type": "text/plain"
                    },
                    "key": "Authorization",
                    "value": "<token>"
                  },
                  {
                    "key": "Accept",
                    "value": "application/json"
                  }
                ],
                "method": "GET",
                "body": {}
              },
              "status": "Forbidden",
              "code": 403,
              "header": [
                {
                  "key": "Content-Type",
                  "value": "application/json"
                }
              ],
              "body": "{\n  \"error\": \"string\"\n}",
              "cookie": [],
              "_postman_previewlanguage": "json"
            }
          ],
          "event": [],
          "protocolProfileBehavior": {
            "disableBodyPruning": true
          }
        },
        {
          "id": "8b9247d2-7a37-4fb3-9c02-de39be5a1ceb",
          "name": "Workday Integration Retrieve a specific learning course",
          "request": {
            "name": "Workday Integration Retrieve a specific learning course",
            "description": {
              "content": "Returns the specified learning course with its content and configuration.",
              "type": "text/plain"
            },
            "url": {
              "path": [
                "learningCourses",
                ":ID"
              ],
              "host": [
                "{{baseUrl}}"
              ],
              "query": [],
              "variable": [
                {
                  "disabled": false,
                  "type": "any",
                  "value": "<string>",
                  "key": "ID",
                  "description": "(Required) "
                },
                {
                  "description": {
                    "content": "",
                    "type": "text/plain"
                  },
                  "type": "any",
                  "value": "{{baseUrl}}",
                  "key": "baseUrl"
                },
                {
                  "description": {
                    "content": "",
                    "type": "text/plain"
                  },
                  "type": "any",
                  "value": "{{tenant}}",
                  "key": "tenant"
                }
              ]
            },
            "header": [
              {
                "key": "Accept",
                "value": "application/json"
              }
            ],
            "method": "GET",
            "auth": null
          },
          "response": [
            {
              "id": "deef1b3c-8f27-48fb-8a29-746702b01825",
              "name": "Successful response with the learning course",
              "originalRequest": {
                "url": {
                  "path": [
                    "learningCourses",
                    ":ID"
                  ],
                  "host": [
                    "{{baseUrl}}"
                  ],
                  "query": [],
                  "variable": [
                    {
                      "disabled": false,
                      "type": "any",
                      "value": "<string>",
                      "key": "ID",
                      "description": "(Required) "
                    },
                    {
                      "description": {
                        "content": "",
                        "type": "text/plain"
                      },
                      "type": "any",
                      "value": "{{baseUrl}}",
                      "key": "baseUrl"
                    },
                    {
                      "description": {
                        "content": "",
                        "type": "text/plain"
                      },
                      "type": "any",
                      "value": "{{tenant}}",
                      "key": "tenant"
                    }
                  ]
                },
                "header": [
                  {
                    "description": {
                      "content": "Added as a part of security scheme: oauth2",
                      "type": "text/plain"
                    },
                    "key": "Authorization",
                    "value": "<token>"
                  },
                  {
                    "key": "Accept",
                    "value": "application/json"
                  }
                ],
                "method": "GET",
                "body": {}
              },
              "status": "OK",
              "code": 200,
              "header": [
                {
                  "key": "Content-Type",
                  "value": "application/json"
                }
              ],
              "body": "{\n  \"id\": \"string\",\n  \"descriptor\": \"string\",\n  \"title\": \"string\",\n  \"description\": \"string\",\n  \"courseType\": {\n    \"id\": \"string\",\n    \"descriptor\": \"string\",\n    \"href\": \"http://kg.mxzaY-KWi2xxRDlmhMPM6C61x+VuLEZWv0W2Pnp1ItXwnAi-wHwFlwIOKIVSAc8VNZC\"\n  },\n  \"duration\": \"string\",\n  \"isActive\": false\n}",
              "cookie": [],
              "_postman_previewlanguage": "json"
            },
            {
              "id": "f2b6d0e2-c1be-4bde-be15-41530f01cf96",
              "name": "Authentication required",
              "originalRequest": {
                "url": {
                  "path": [
                    "learningCourses",
                    ":ID"
                  ],
                  "host": [
                    "{{baseUrl}}"
                  ],
                  "query": [],
                  "variable": [
                    {
                      "disabled": false,
                      "type": "any",
                      "value": "<string>",
                      "key": "ID",
                      "description": "(Required) "
                    },
                    {
                      "description": {
                        "content": "",
                        "type": "text/plain"
                      },
                      "type": "any",
                      "value": "{{baseUrl}}",
                      "key": "baseUrl"
                    },
                    {
                      "description": {
                        "content": "",
                        "type": "text/plain"
                      },
                      "type": "any",
                      "value": "{{tenant}}",
                      "key": "tenant"
                    }
                  ]
                },
                "header": [
                  {
                    "description": {
                      "content": "Added as a part of security scheme: oauth2",
                      "type": "text/plain"
                    },
                    "key": "Authorization",
                    "value": "<token>"
                  },
                  {
                    "key": "Accept",
                    "value": "application/json"
                  }
                ],
                "method": "GET",
                "body": {}
              },
              "status": "Unauthorized",
              "code": 401,
              "header": [
                {
                  "key": "Content-Type",
                  "value": "application/json"
                }
              ],
              "body": "{\n  \"error\": \"string\"\n}",
              "cookie": [],
              "_postman_previewlanguage": "json"
            },
            {
              "id": "57e14432-04c9-4130-aae8-ccdf56b4b3c5",
              "name": "Insufficient permissions",
              "originalRequest": {
                "url": {
                  "path": [
                    "learningCourses",
                    ":ID"
                  ],
                  "host": [
                    "{{baseUrl}}"
                  ],
                  "query": [],
                  "variable": [
                    {
                      "disabled": false,
                      "type": "any",
                      "value": "<string>",
                      "key": "ID",
                      "description": "(Required) "
                    },
                    {
                      "description": {
                        "content": "",
                        "type": "text/plain"
                      },
                      "type": "any",
                      "value": "{{baseUrl}}",
                      "key": "baseUrl"
                    },
                    {
                      "description": {
                        "content": "",
                        "type": "text/plain"
                      },
                      "type": "any",
                      "value": "{{tenant}}",
                      "key": "tenant"
                    }
                  ]
                },
                "header": [
                  {
                    "description": {
                      "content": "Added as a part of security scheme: oauth2",
                      "type": "text/plain"
                    },
                    "key": "Authorization",
                    "value": "<token>"
                  },
                  {
                    "key": "Accept",
                    "value": "application/json"
                  }
                ],
                "method": "GET",
                "body": {}
              },
              "status": "Forbidden",
              "code": 403,
              "header": [
                {
                  "key": "Content-Type",
                  "value": "application/json"
                }
              ],
              "body": "{\n  \"error\": \"string\"\n}",
              "cookie": [],
              "_postman_previewlanguage": "json"
            },
            {
              "id": "6128c848-30c5-4e25-95b2-631444a3a44b",
              "name": "Resource not found",
              "originalRequest": {
                "url": {
                  "path": [
                    "learningCourses",
                    ":ID"
                  ],
                  "host": [
                    "{{baseUrl}}"
                  ],
                  "query": [],
                  "variable": [
                    {
                      "disabled": false,
                      "type": "any",
                      "value": "<string>",
                      "key": "ID",
                      "description": "(Required) "
                    },
                    {
                      "description": {
                        "content": "",
                        "type": "text/plain"
                      },
                      "type": "any",
                      "value": "{{baseUrl}}",
                      "key": "baseUrl"
                    },
                    {
                      "description": {
                        "content": "",
                        "type": "text/plain"
                      },
                      "type": "any",
                      "value": "{{tenant}}",
                      "key": "tenant"
                    }
                  ]
                },
                "header": [
                  {
                    "description": {
                      "content": "Added as a part of security scheme: oauth2",
                      "type": "text/plain"
                    },
                    "key": "Authorization",
                    "value": "<token>"
                  },
                  {
                    "key": "Accept",
                    "value": "application/json"
                  }
                ],
                "method": "GET",
                "body": {}
              },
              "status": "Not Found",
              "code": 404,
              "header": [
                {
                  "key": "Content-Type",
                  "value": "application/json"
                }
              ],
              "body": "{\n  \"error\": \"string\"\n}",
              "cookie": [],
              "_postman_previewlanguage": "json"
            }
          ],
          "event": [],
          "protocolProfileBehavior": {
            "disableBodyPruning": true
          }
        }
      ],
      "event": []
    }
  ],
  "event": [],
  "variable": [
    {
      "description": {
        "content": "",
        "type": "text/plain"
      },
      "type": "any",
      "value": "wd2-impl-services1.workday.com",
      "key": "baseUrl"
    },
    {
      "description": {
        "content": "",
        "type": "text/plain"
      },
      "type": "any",
      "value": "tenant",
      "key": "tenant"
    },
    {
      "type": "string",
      "value": "https://{{baseUrl}}/ccx/api/learning/v1/{{tenant}}",
      "key": "baseUrl"
    }
  ],
  "auth": {
    "type": "oauth2",
    "oauth2": [
      {
        "key": "scope",
        "value": "r:learning"
      },
      {
        "key": "accessTokenUrl",
        "value": "https://{baseUrl}/oauth2/{tenant}/token"
      },
      {
        "key": "authUrl",
        "value": "https://{baseUrl}/authorize"
      },
      {
        "key": "grant_type",
        "value": "authorization_code"
      }
    ]
  },
  "info": {
    "_postman_id": "267c3b67-8e47-4501-9024-166301a19a4a",
    "name": "Workday Integration Workday Learning API",
    "schema": "https://schema.getpostman.com/json/collection/v2.1.0/collection.json",
    "description": {
      "content": "API for managing learning and development within the Workday Learning module. Provides access to course catalogs, learning assignments, enrollment data, and training completion records.\n\nContact Support:\n Name: Workday API Support\n Email: api-support@workday.com",
      "type": "text/plain"
    }
  }
}