{
  "item": [
    {
      "id": "a14277cd-6e9a-41a1-b742-af2920ddddd5",
      "name": "Requests",
      "description": {
        "content": "",
        "type": "text/plain"
      },
      "item": [
        {
          "id": "734208c4-7d44-404e-8597-53511c5cbdde",
          "name": "Workday Integration Retrieve a collection of requests",
          "request": {
            "name": "Workday Integration Retrieve a collection of requests",
            "description": {
              "content": "Returns a collection of requests from the Workday Requests API.",
              "type": "text/plain"
            },
            "url": {
              "path": [
                "requests"
              ],
              "host": [
                "{{baseUrl}}"
              ],
              "query": [
                {
                  "disabled": false,
                  "key": "limit",
                  "value": "20"
                },
                {
                  "disabled": false,
                  "key": "offset",
                  "value": "0"
                },
                {
                  "disabled": false,
                  "key": "search",
                  "value": "<string>"
                }
              ],
              "variable": [
                {
                  "description": {
                    "content": "",
                    "type": "text/plain"
                  },
                  "type": "any",
                  "value": "{{baseUrl}}",
                  "key": "baseUrl"
                },
                {
                  "description": {
                    "content": "",
                    "type": "text/plain"
                  },
                  "type": "any",
                  "value": "{{tenant}}",
                  "key": "tenant"
                }
              ]
            },
            "header": [
              {
                "key": "Accept",
                "value": "application/json"
              }
            ],
            "method": "GET",
            "auth": null
          },
          "response": [
            {
              "id": "ba8edda0-be8b-4bf8-8c62-a0708ab7bd1d",
              "name": "Successful response with requests",
              "originalRequest": {
                "url": {
                  "path": [
                    "requests"
                  ],
                  "host": [
                    "{{baseUrl}}"
                  ],
                  "query": [
                    {
                      "key": "limit",
                      "value": "20"
                    },
                    {
                      "key": "offset",
                      "value": "0"
                    },
                    {
                      "key": "search",
                      "value": "<string>"
                    }
                  ],
                  "variable": [
                    {
                      "description": {
                        "content": "",
                        "type": "text/plain"
                      },
                      "type": "any",
                      "value": "{{baseUrl}}",
                      "key": "baseUrl"
                    },
                    {
                      "description": {
                        "content": "",
                        "type": "text/plain"
                      },
                      "type": "any",
                      "value": "{{tenant}}",
                      "key": "tenant"
                    }
                  ]
                },
                "header": [
                  {
                    "description": {
                      "content": "Added as a part of security scheme: oauth2",
                      "type": "text/plain"
                    },
                    "key": "Authorization",
                    "value": "<token>"
                  },
                  {
                    "key": "Accept",
                    "value": "application/json"
                  }
                ],
                "method": "GET",
                "body": {}
              },
              "status": "OK",
              "code": 200,
              "header": [
                {
                  "key": "Content-Type",
                  "value": "application/json"
                }
              ],
              "body": "{\n  \"total\": 1358,\n  \"data\": [\n    {\n      \"id\": \"string\",\n      \"descriptor\": \"string\",\n      \"href\": \"http://yhXNvp.cyBCVCiQzkIOqjvTh1VHCFcS5KPPFmnmZm+v9GgJ43eLWxgG-kZRiT3FDg5D8oOsSEgBr\"\n    },\n    {\n      \"id\": \"string\",\n      \"descriptor\": \"string\",\n      \"href\": \"http://YkMysSNKRVvvNeJbwzTYL.hlspkuUG3JeAunIkh.fXepHCAkcu0Yl-vovSTizgcaioupy4-p\"\n    }\n  ]\n}",
              "cookie": [],
              "_postman_previewlanguage": "json"
            },
            {
              "id": "7a89d83c-1048-4ac1-9e01-d17ac7306ae2",
              "name": "Authentication required",
              "originalRequest": {
                "url": {
                  "path": [
                    "requests"
                  ],
                  "host": [
                    "{{baseUrl}}"
                  ],
                  "query": [
                    {
                      "key": "limit",
                      "value": "20"
                    },
                    {
                      "key": "offset",
                      "value": "0"
                    },
                    {
                      "key": "search",
                      "value": "<string>"
                    }
                  ],
                  "variable": [
                    {
                      "description": {
                        "content": "",
                        "type": "text/plain"
                      },
                      "type": "any",
                      "value": "{{baseUrl}}",
                      "key": "baseUrl"
                    },
                    {
                      "description": {
                        "content": "",
                        "type": "text/plain"
                      },
                      "type": "any",
                      "value": "{{tenant}}",
                      "key": "tenant"
                    }
                  ]
                },
                "header": [
                  {
                    "description": {
                      "content": "Added as a part of security scheme: oauth2",
                      "type": "text/plain"
                    },
                    "key": "Authorization",
                    "value": "<token>"
                  },
                  {
                    "key": "Accept",
                    "value": "application/json"
                  }
                ],
                "method": "GET",
                "body": {}
              },
              "status": "Unauthorized",
              "code": 401,
              "header": [
                {
                  "key": "Content-Type",
                  "value": "application/json"
                }
              ],
              "body": "{\n  \"error\": \"string\"\n}",
              "cookie": [],
              "_postman_previewlanguage": "json"
            },
            {
              "id": "1e21f3ac-13b2-46e2-a5cc-c59ef287a1df",
              "name": "Insufficient permissions",
              "originalRequest": {
                "url": {
                  "path": [
                    "requests"
                  ],
                  "host": [
                    "{{baseUrl}}"
                  ],
                  "query": [
                    {
                      "key": "limit",
                      "value": "20"
                    },
                    {
                      "key": "offset",
                      "value": "0"
                    },
                    {
                      "key": "search",
                      "value": "<string>"
                    }
                  ],
                  "variable": [
                    {
                      "description": {
                        "content": "",
                        "type": "text/plain"
                      },
                      "type": "any",
                      "value": "{{baseUrl}}",
                      "key": "baseUrl"
                    },
                    {
                      "description": {
                        "content": "",
                        "type": "text/plain"
                      },
                      "type": "any",
                      "value": "{{tenant}}",
                      "key": "tenant"
                    }
                  ]
                },
                "header": [
                  {
                    "description": {
                      "content": "Added as a part of security scheme: oauth2",
                      "type": "text/plain"
                    },
                    "key": "Authorization",
                    "value": "<token>"
                  },
                  {
                    "key": "Accept",
                    "value": "application/json"
                  }
                ],
                "method": "GET",
                "body": {}
              },
              "status": "Forbidden",
              "code": 403,
              "header": [
                {
                  "key": "Content-Type",
                  "value": "application/json"
                }
              ],
              "body": "{\n  \"error\": \"string\"\n}",
              "cookie": [],
              "_postman_previewlanguage": "json"
            }
          ],
          "event": [],
          "protocolProfileBehavior": {
            "disableBodyPruning": true
          }
        },
        {
          "id": "03fdd7a1-f836-4e74-91c7-3d6f3384d033",
          "name": "Workday Integration Retrieve a specific Request",
          "request": {
            "name": "Workday Integration Retrieve a specific Request",
            "description": {
              "content": "Returns the specified Request instance with its details.",
              "type": "text/plain"
            },
            "url": {
              "path": [
                "requests",
                ":ID"
              ],
              "host": [
                "{{baseUrl}}"
              ],
              "query": [],
              "variable": [
                {
                  "disabled": false,
                  "type": "any",
                  "value": "<string>",
                  "key": "ID",
                  "description": "(Required) "
                },
                {
                  "description": {
                    "content": "",
                    "type": "text/plain"
                  },
                  "type": "any",
                  "value": "{{baseUrl}}",
                  "key": "baseUrl"
                },
                {
                  "description": {
                    "content": "",
                    "type": "text/plain"
                  },
                  "type": "any",
                  "value": "{{tenant}}",
                  "key": "tenant"
                }
              ]
            },
            "header": [
              {
                "key": "Accept",
                "value": "application/json"
              }
            ],
            "method": "GET",
            "auth": null
          },
          "response": [
            {
              "id": "f6443481-93f8-401b-b377-ecf8366f0101",
              "name": "Successful response with the Request",
              "originalRequest": {
                "url": {
                  "path": [
                    "requests",
                    ":ID"
                  ],
                  "host": [
                    "{{baseUrl}}"
                  ],
                  "query": [],
                  "variable": [
                    {
                      "disabled": false,
                      "type": "any",
                      "value": "<string>",
                      "key": "ID",
                      "description": "(Required) "
                    },
                    {
                      "description": {
                        "content": "",
                        "type": "text/plain"
                      },
                      "type": "any",
                      "value": "{{baseUrl}}",
                      "key": "baseUrl"
                    },
                    {
                      "description": {
                        "content": "",
                        "type": "text/plain"
                      },
                      "type": "any",
                      "value": "{{tenant}}",
                      "key": "tenant"
                    }
                  ]
                },
                "header": [
                  {
                    "description": {
                      "content": "Added as a part of security scheme: oauth2",
                      "type": "text/plain"
                    },
                    "key": "Authorization",
                    "value": "<token>"
                  },
                  {
                    "key": "Accept",
                    "value": "application/json"
                  }
                ],
                "method": "GET",
                "body": {}
              },
              "status": "OK",
              "code": 200,
              "header": [
                {
                  "key": "Content-Type",
                  "value": "application/json"
                }
              ],
              "body": "{\n  \"id\": \"string\",\n  \"descriptor\": \"string\",\n  \"href\": \"http://tduPueOhPxGN.blh5dPxV.PoeF\"\n}",
              "cookie": [],
              "_postman_previewlanguage": "json"
            },
            {
              "id": "4bb58d15-ed54-44b3-8714-22b7093f4103",
              "name": "Authentication required",
              "originalRequest": {
                "url": {
                  "path": [
                    "requests",
                    ":ID"
                  ],
                  "host": [
                    "{{baseUrl}}"
                  ],
                  "query": [],
                  "variable": [
                    {
                      "disabled": false,
                      "type": "any",
                      "value": "<string>",
                      "key": "ID",
                      "description": "(Required) "
                    },
                    {
                      "description": {
                        "content": "",
                        "type": "text/plain"
                      },
                      "type": "any",
                      "value": "{{baseUrl}}",
                      "key": "baseUrl"
                    },
                    {
                      "description": {
                        "content": "",
                        "type": "text/plain"
                      },
                      "type": "any",
                      "value": "{{tenant}}",
                      "key": "tenant"
                    }
                  ]
                },
                "header": [
                  {
                    "description": {
                      "content": "Added as a part of security scheme: oauth2",
                      "type": "text/plain"
                    },
                    "key": "Authorization",
                    "value": "<token>"
                  },
                  {
                    "key": "Accept",
                    "value": "application/json"
                  }
                ],
                "method": "GET",
                "body": {}
              },
              "status": "Unauthorized",
              "code": 401,
              "header": [
                {
                  "key": "Content-Type",
                  "value": "application/json"
                }
              ],
              "body": "{\n  \"error\": \"string\"\n}",
              "cookie": [],
              "_postman_previewlanguage": "json"
            },
            {
              "id": "322c2031-901f-4ee4-a4fa-e5b4f34e26bd",
              "name": "Insufficient permissions",
              "originalRequest": {
                "url": {
                  "path": [
                    "requests",
                    ":ID"
                  ],
                  "host": [
                    "{{baseUrl}}"
                  ],
                  "query": [],
                  "variable": [
                    {
                      "disabled": false,
                      "type": "any",
                      "value": "<string>",
                      "key": "ID",
                      "description": "(Required) "
                    },
                    {
                      "description": {
                        "content": "",
                        "type": "text/plain"
                      },
                      "type": "any",
                      "value": "{{baseUrl}}",
                      "key": "baseUrl"
                    },
                    {
                      "description": {
                        "content": "",
                        "type": "text/plain"
                      },
                      "type": "any",
                      "value": "{{tenant}}",
                      "key": "tenant"
                    }
                  ]
                },
                "header": [
                  {
                    "description": {
                      "content": "Added as a part of security scheme: oauth2",
                      "type": "text/plain"
                    },
                    "key": "Authorization",
                    "value": "<token>"
                  },
                  {
                    "key": "Accept",
                    "value": "application/json"
                  }
                ],
                "method": "GET",
                "body": {}
              },
              "status": "Forbidden",
              "code": 403,
              "header": [
                {
                  "key": "Content-Type",
                  "value": "application/json"
                }
              ],
              "body": "{\n  \"error\": \"string\"\n}",
              "cookie": [],
              "_postman_previewlanguage": "json"
            },
            {
              "id": "f5086d0e-0ea8-4337-978a-68c6a72c34b8",
              "name": "Resource not found",
              "originalRequest": {
                "url": {
                  "path": [
                    "requests",
                    ":ID"
                  ],
                  "host": [
                    "{{baseUrl}}"
                  ],
                  "query": [],
                  "variable": [
                    {
                      "disabled": false,
                      "type": "any",
                      "value": "<string>",
                      "key": "ID",
                      "description": "(Required) "
                    },
                    {
                      "description": {
                        "content": "",
                        "type": "text/plain"
                      },
                      "type": "any",
                      "value": "{{baseUrl}}",
                      "key": "baseUrl"
                    },
                    {
                      "description": {
                        "content": "",
                        "type": "text/plain"
                      },
                      "type": "any",
                      "value": "{{tenant}}",
                      "key": "tenant"
                    }
                  ]
                },
                "header": [
                  {
                    "description": {
                      "content": "Added as a part of security scheme: oauth2",
                      "type": "text/plain"
                    },
                    "key": "Authorization",
                    "value": "<token>"
                  },
                  {
                    "key": "Accept",
                    "value": "application/json"
                  }
                ],
                "method": "GET",
                "body": {}
              },
              "status": "Not Found",
              "code": 404,
              "header": [
                {
                  "key": "Content-Type",
                  "value": "application/json"
                }
              ],
              "body": "{\n  \"error\": \"string\"\n}",
              "cookie": [],
              "_postman_previewlanguage": "json"
            }
          ],
          "event": [],
          "protocolProfileBehavior": {
            "disableBodyPruning": true
          }
        }
      ],
      "event": []
    }
  ],
  "event": [],
  "variable": [
    {
      "description": {
        "content": "",
        "type": "text/plain"
      },
      "type": "any",
      "value": "wd2-impl-services1.workday.com",
      "key": "baseUrl"
    },
    {
      "description": {
        "content": "",
        "type": "text/plain"
      },
      "type": "any",
      "value": "tenant",
      "key": "tenant"
    },
    {
      "type": "string",
      "value": "https://{{baseUrl}}/ccx/api/requests/v1/{{tenant}}",
      "key": "baseUrl"
    }
  ],
  "auth": {
    "type": "oauth2",
    "oauth2": [
      {
        "key": "scope",
        "value": "r:requests"
      },
      {
        "key": "accessTokenUrl",
        "value": "https://{baseUrl}/oauth2/{tenant}/token"
      },
      {
        "key": "authUrl",
        "value": "https://{baseUrl}/authorize"
      },
      {
        "key": "grant_type",
        "value": "authorization_code"
      }
    ]
  },
  "info": {
    "_postman_id": "edcd7ada-c537-44b0-ad88-9f0b797ec71d",
    "name": "Workday Integration Workday Requests API",
    "schema": "https://schema.getpostman.com/json/collection/v2.1.0/collection.json",
    "description": {
      "content": "API for managing service requests and approval workflows within Workday. Supports request creation, routing, approval chains, and status tracking.\n\nContact Support:\n Name: Workday API Support\n Email: api-support@workday.com",
      "type": "text/plain"
    }
  }
}